semby/cli/__init__.py
semby/core/__init__.py
semby/core/lexer.py
semby/core/parser.py
semby/core/vm.py
semby-1.0.5.dist-info/entry_points.txt
semby-1.0.5.dist-info/LICENSE
semby-1.0.5.dist-info/WHEEL
semby-1.0.5.dist-info/METADATA
semby-1.0.5.dist-info/RECORD
