Metadata-Version: 2.1
Name: semby
Version: 1.0.5
Summary: A simple stack based assembly like programming language
Home-page: https://github.com/vcokltfre/semby
License: MIT
Author: vcokltfre
Author-email: vcokltfre@gmail.com
Requires-Python: >=3.10,<4.0
Classifier: License :: OSI Approved :: MIT License
Classifier: Programming Language :: Python :: 3
Classifier: Programming Language :: Python :: 3.10
Requires-Dist: typer (>=0.4.0,<0.5.0)
Project-URL: Repository, https://github.com/vcokltfre/semby
